a2a_proxy_server/__init__.py
a2a_proxy_server/agent.py
a2a_proxy_server/server.py
a2a_proxy_server/task_manager.py
a2a_proxy_server/configs/sample-agent.yml
a2a_proxy_server-0.1.3.dist-info/METADATA
a2a_proxy_server-0.1.3.dist-info/WHEEL
a2a_proxy_server-0.1.3.dist-info/entry_points.txt
a2a_proxy_server-0.1.3.dist-info/RECORD
